fox_progress_bar/__init__.py
fox_progress_bar/cli.py
fox_progress_bar/progress.py
fox_progress_bar-0.1.3.dist-info/licenses/LICENSE
fox_progress_bar-0.1.3.dist-info/METADATA
fox_progress_bar-0.1.3.dist-info/WHEEL
fox_progress_bar-0.1.3.dist-info/entry_points.txt
fox_progress_bar-0.1.3.dist-info/top_level.txt
fox_progress_bar-0.1.3.dist-info/RECORD
