Metadata-Version: 2.4
Name: fox-progress-bar
Version: 0.1.3
Summary: A tiny terminal progress bar with a fox emoji.
Author: Mozilla Data Collective
License:                                  Apache License
Project-URL: Homepage, https://github.com/Mozilla-Data-Collective/fox-progress-bar
Project-URL: Repository, https://github.com/Mozilla-Data-Collective/fox-progress-bar
Project-URL: Issues, https://github.com/Mozilla-Data-Collective/fox-progress-bar/issues
Keywords: progress,progressbar,terminal,emoji,cli,fox
Requires-Python: >=3.8
License-File: LICENSE
Dynamic: license-file
